setup.py
alphaDigger.egg-info/PKG-INFO
alphaDigger.egg-info/SOURCES.txt
alphaDigger.egg-info/dependency_links.txt
alphaDigger.egg-info/top_level.txt
alphaSeeker/__init__.py
alphaSeeker/alphaSeeker.py